qmeans/__init__.py
qmeans/qkmeans.py
qmeans-0.1.2.dist-info/LICENSE
qmeans-0.1.2.dist-info/METADATA
qmeans-0.1.2.dist-info/WHEEL
qmeans-0.1.2.dist-info/top_level.txt
qmeans-0.1.2.dist-info/RECORD
