Metadata-Version: 2.1
Name: qmeans
Version: 0.1.2
Summary: Q-Means algorithm implementation using Qiskit compatible with Scikit-Learn.
Home-page: http://qmeans.readthedocs.io/
Author: David Quiroga
Author-email: raijeku@gmail.com
License: Apache-2.0
License-File: LICENSE
Requires-Dist: wheel
Requires-Dist: twine
Requires-Dist: setuptools
Requires-Dist: numpy (==1.23.5)
Requires-Dist: pandas (==1.5.2)
Requires-Dist: qiskit (==0.41.1)
Requires-Dist: scikit-learn (==1.0.2)
Requires-Dist: pytest
Requires-Dist: hypothesis
Requires-Dist: sphinx
Requires-Dist: sphinx-rtd-theme
Requires-Dist: sphinxcontrib-napoleon
